esqa/__init__.py
esqa/asserts/__init__.py
esqa/asserts/base.py
esqa/asserts/equal.py
esqa/asserts/higher.py
esqa/asserts/lower.py
esqa/cli.py
esqa/constants.py
esqa/distance.py
esqa/error.py
esqa/save.py
esqa/validation_config.py
esqa/validator.py
esqa-0.4.2.dist-info/entry_points.txt
esqa-0.4.2.dist-info/LICENSE
esqa-0.4.2.dist-info/WHEEL
esqa-0.4.2.dist-info/METADATA
esqa-0.4.2.dist-info/RECORD
