Metadata-Version: 2.1
Name: esqa
Version: 0.4.2
Summary: Tiny tool to checks the search qualities of the Elasticsearch indices.
Author: Takahiko Ito
Author-email: takahiko.ito@dr-ubie.com
Requires-Python: >=3.7,<4.0
Classifier: Programming Language :: Python :: 3
Classifier: Programming Language :: Python :: 3.10
Classifier: Programming Language :: Python :: 3.7
Classifier: Programming Language :: Python :: 3.8
Classifier: Programming Language :: Python :: 3.9
Requires-Dist: click (>=8.0.0)
Requires-Dist: elasticsearch (==7.10.1)
Requires-Dist: rbo (>=0.1.2,<0.2.0)
